{
  "246438624": {
    "missing_days": 14
  },
  "142044104": {
    "missing_days": 14
  },
  "967397633": {
    "missing_days": 11
  },
  "92442613": {
    "missing_days": 13
  },
  "148825454": {
    "missing_days": 13
  },
  "197560872": {
    "missing_days": 11
  },
  "41002668": {
    "missing_days": 12
  },
  "246442159": {
    "missing_days": 12
  },
  "71713814": {
    "missing_days": 13
  },
  "283184886": {
    "missing_days": 14
  },
  "139625239": {
    "missing_days": 12
  },
  "246443845": {
    "missing_days": 13
  }
}